aouyi_mcp_demo/__init__.py
developer_tools_mcp-1.0.0.dist-info/METADATA
developer_tools_mcp-1.0.0.dist-info/WHEEL
developer_tools_mcp-1.0.0.dist-info/top_level.txt
developer_tools_mcp-1.0.0.dist-info/RECORD
