Metadata-Version: 2.4
Name: developer-tools-mcp
Version: 1.0.0
Summary: 开发者工具 MCP 服务器 - 提供代码格式化、文件操作和项目分析等开发者常用功能
Author-email: MCP Developer <developer@example.com>
Keywords: mcp,developer-tools,code-formatting,file-operations
Classifier: Development Status :: 4 - Beta
Classifier: Intended Audience :: Developers
Classifier: Programming Language :: Python :: 3.13
Requires-Python: >=3.13
Requires-Dist: mcp[cli]>=1.13.0
